NOTICE.txt
ipydeck/__init__.py
ipydeck/base_map.py
ipydeck/deck.py
ipydeck/utils.py
ipydeck/view_state.py
ipydeck/layers/__init__.py
ipydeck/layers/base.py
ipydeck/layers/bitmap_tile.py
ipydeck/layers/geojson.py
ipydeck/layers/line.py
ipydeck/static/widget.css
ipydeck/static/widget.js
ipydeck-0.4.7.dist-info/METADATA
ipydeck-0.4.7.dist-info/WHEEL
ipydeck-0.4.7.dist-info/licenses/LICENSE.txt
ipydeck-0.4.7.dist-info/licenses/NOTICE.txt
ipydeck-0.4.7.dist-info/RECORD
