Metadata-Version: 2.4
Name: ipydeck
Version: 0.4.7
Summary: Yet another Jupyter widget for deck.gl
Project-URL: Homepage, https://ozekik.github.io/ipydeck/
Project-URL: Repository, https://github.com/ozekik/ipydeck
Author-email: Kentaro Ozeki <32771324+ozekik@users.noreply.github.com>
License-Expression: MIT
License-File: LICENSE.txt
License-File: NOTICE.txt
Requires-Python: <4,>=3.10
Requires-Dist: anywidget<0.10,>=0.9.13
